thetadata/__init__.py
thetadata/client.py
thetadata/enums.py
thetadata/exceptions.py
thetadata/parsing.py
thetadata/py.typed
thetadata/terminal.py
thetadata-0.9.10.dist-info/METADATA
thetadata-0.9.10.dist-info/WHEEL
thetadata-0.9.10.dist-info/licenses/LICENSE
thetadata-0.9.10.dist-info/RECORD
