Metadata-Version: 2.1
Name: thetadata
Version: 0.9.10
Summary: Python API for Thetadata
Project-URL: Homepage, https://thetadata.net
Project-URL: Source, https://thetadata-api.github.io/thetadata-python/reference/
Project-URL: Bug Tracker, https://github.com/ThetaData-API/thetadata-python/issues
Project-URL: Documentation, https://thetadata-api.github.io/thetadata-python/
Author-email: Bailey Danseglio <bailey@thetadata.net>, Adler Weber <redacted@thetadata.net>
License: MIT License
License-File: LICENSE
Classifier: License :: OSI Approved :: MIT License
Classifier: Operating System :: OS Independent
Classifier: Programming Language :: Python :: 3
Requires-Python: >=3.7
Requires-Dist: ijson
Requires-Dist: pandas
Requires-Dist: psutil
Requires-Dist: requests
Requires-Dist: tqdm
Requires-Dist: wget
Provides-Extra: docs
Requires-Dist: mkdocs; extra == 'docs'
Requires-Dist: mkdocs-material; extra == 'docs'
Requires-Dist: mkdocstrings[python]; extra == 'docs'
Provides-Extra: tests
Requires-Dist: coverage>=5.0.3; extra == 'tests'
Requires-Dist: pytest; extra == 'tests'
Requires-Dist: pytest-benchmark[histogram]>=3.2.1; extra == 'tests'
